viper/__init__.py
viper/common.py
viper/customLogging.py
viper/download.py
viper/encrypt.py
viper/flash.py
viper/named_lock.py
viper_python-1.0.4.dist-info/LICENSE
viper_python-1.0.4.dist-info/METADATA
viper_python-1.0.4.dist-info/WHEEL
viper_python-1.0.4.dist-info/top_level.txt
viper_python-1.0.4.dist-info/RECORD
