Metadata-Version: 2.1
Name: viper-python
Version: 1.0.4
Summary: Common utility functions.
Home-page: https://github.com/siddhantkushwaha/viper
Download-URL: https://github.com/siddhantkushwaha/viper/archive/1.0.2.tar.gz
Author: Siddhant Kushwaha
Author-email: k16.siddhant@gmail.com
License: MIT
Keywords: DOWNLOAD,PARALLEL,CONCURRENT,LOGGING
Classifier: Development Status :: 3 - Alpha
Classifier: Intended Audience :: Developers
Classifier: Topic :: Software Development :: Build Tools
Classifier: License :: OSI Approved :: MIT License
Classifier: Programming Language :: Python :: 3.6
Classifier: Programming Language :: Python :: 3.7
Classifier: Programming Language :: Python :: 3.8
Classifier: Programming Language :: Python :: 3.9
License-File: LICENSE
Requires-Dist: requests
